zdktest/__init__.py
zdktest/zdktest.py
zdktest-0.0.2.dist-info/METADATA
zdktest-0.0.2.dist-info/WHEEL
zdktest-0.0.2.dist-info/top_level.txt
zdktest-0.0.2.dist-info/RECORD
