Metadata-Version: 2.1
Name: zdktest
Version: 0.0.2
Summary: just a simple test
Home-page: UNKNOWN
Author: ZDK
Author-email: zhoudk@ihep.ac.cn
License: MIT License
Keywords: simple,test
Platform: any
